{"analysisResults":[[{"matchingRatio":0.9429948594835069,"averageDistanceRatio":0.000007093005461685954,"mismatchingAverageDistanceRatio":0.00012442747088104738},{"matchingRatio":0.99737548828125,"averageDistanceRatio":0.000006408445478651481,"mismatchingAverageDistanceRatio":0.0024701637509010653},{"matchingRatio":0.9995439317491319,"averageDistanceRatio":0.000004090776580314868,"mismatchingAverageDistanceRatio":0.011809357749184323}],[{"matchingRatio":0.055199517144097224,"averageDistanceRatio":0.0003628335029311868,"mismatchingAverageDistanceRatio":0.0003840318771159272},{"matchingRatio":0.1361151801215278,"averageDistanceRatio":0.0003371473458571197,"mismatchingAverageDistanceRatio":0.0004186658522710679},{"matchingRatio":0.976409912109375,"averageDistanceRatio":0.00003836395743243993,"mismatchingAverageDistanceRatio":0.004465973451345542}]],"lighting":"../../../shared-assets/environments/lightroom_14b.hdr","dimensions":{"width":768,"height":768},"target":{"x":0,"y":0.75,"z":0},"orbit":{"theta":0,"phi":90,"radius":2},"verticalFoV":45,"name":"khronos-CesiumMan","model":"../../../shared-assets/models/glTF-Sample-Models/2.0/CesiumMan/glTF/CesiumMan.gltf"}